LICENSE
README.md
beancount_import_sparkasse/__init__.py
beancount_import_sparkasse/giro.py
beancount_import_sparkasse-0.0.1a0.dist-info/LICENSE
beancount_import_sparkasse-0.0.1a0.dist-info/WHEEL
beancount_import_sparkasse-0.0.1a0.dist-info/METADATA
beancount_import_sparkasse-0.0.1a0.dist-info/RECORD
