Metadata-Version: 2.1
Name: beancount-import-sparkasse
Version: 0.0.1a0
Summary: Beancount importer plugin for Sparkasse CSV-CAMT exports
Home-page: https://github.com/laermannjan/beancount-import-sparkasse
License: MIT
Keywords: beancount,plain-text-accounting,ledger,sparkasse
Author: Jan Laermann
Author-email: laermannjan@gmail.com
Requires-Python: >=3.9,<4.0
Classifier: Development Status :: 2 - Pre-Alpha
Classifier: Environment :: Console
Classifier: Environment :: Plugins
Classifier: Intended Audience :: Developers
Classifier: Intended Audience :: End Users/Desktop
Classifier: Intended Audience :: Financial and Insurance Industry
Classifier: License :: OSI Approved :: MIT License
Classifier: Programming Language :: Python :: 3
Classifier: Programming Language :: Python :: 3.10
Classifier: Programming Language :: Python :: 3.9
Classifier: Topic :: Office/Business :: Financial :: Accounting
Classifier: Topic :: Text Processing
Classifier: Typing :: Typed
Requires-Dist: beancount (>=2.3.5,<3.0.0)
Project-URL: Repository, https://github.com/laermannjan/beancount-import-sparkasse
